fcntl.py
alphafed/__init__.py
alphafed/fs.py
alphafed/loggers.py
alphafed/mock.py
alphafed/perf_bench.py
alphafed/scheduler.py
alphafed/utils.py
alphafed/auto_ml/__init__.py
alphafed/auto_ml/auto_model.py
alphafed/auto_ml/exceptions.py
alphafed/auto_ml/pretrained.py
alphafed/auto_ml/cvat/__init__.py
alphafed/auto_ml/cvat/annotation.py
alphafed/contractor/__init__.py
alphafed/contractor/common.py
alphafed/contractor/task_contractor.py
alphafed/contractor/task_message_contractor.py
alphafed/data_channel/__init__.py
alphafed/data_channel/data_channel.py
alphafed/data_channel/data_channel_pb2.py
alphafed/data_channel/data_channel_pb2_grpc.py
alphafed/data_channel/grpc_data_channel.py
alphafed/data_channel/shared_file_data_channel.py
alphafed/dataset/__init__.py
alphafed/dataset/mnist.py
alphafed/docs/auto_ml/res/auto.py
alphafed/docs/auto_ml/res/res_net.py
alphafed/docs/customized_scheduler/contractor.py
alphafed/docs/customized_scheduler/scheduler.py
alphafed/docs/customized_scheduler/simple_task.py
alphafed/docs/fed_avg/net.py
alphafed/docs/mock/net.py
alphafed/docs/mock/scheduler.py
alphafed/docs/tutorial/res/cnn_net.py
alphafed/docs/tutorial/res/auto_model_fed_avg/auto_fed_avg.py
alphafed/docs/tutorial/res/auto_model_fed_avg/res_net.py
alphafed/docs/tutorial/res/auto_model_local/auto.py
alphafed/docs/tutorial/res/auto_model_local/res_net.py
alphafed/docs/tutorial/res/simple_fed_avg/contractor.py
alphafed/docs/tutorial/res/simple_fed_avg/scheduler.py
alphafed/examples/__init__.py
alphafed/examples/auto_ml/__init__.py
alphafed/examples/auto_ml/breast_density_classification/__init__.py
alphafed/examples/auto_ml/breast_density_classification/clean_history_msg.py
alphafed/examples/auto_ml/breast_density_classification/run_aggregator.py
alphafed/examples/auto_ml/breast_density_classification/run_data_owner_2.py
alphafed/examples/auto_ml/breast_density_classification/run_data_owner_4.py
alphafed/examples/auto_ml/breast_density_classification/run_local.py
alphamed_federated-0.4.9.dist-info/LICENSE
alphamed_federated-0.4.9.dist-info/METADATA
alphamed_federated-0.4.9.dist-info/WHEEL
alphamed_federated-0.4.9.dist-info/top_level.txt
alphamed_federated-0.4.9.dist-info/RECORD
