Metadata-Version: 2.1
Name: alphamed-federated
Version: 0.4.9
Summary: AlphaMed Federated Learning Module
Author-email: Huang Yi Chun <huangyichun@jinghang.ai>
License: Apache License
Project-URL: Homepage, https://github.com/ssplabs/alphafed
Project-URL: Bug Tracker, https://github.com/ssplabs/alphafed/issues
Classifier: Programming Language :: Python :: 3
Classifier: License :: OSI Approved :: Apache Software License
Classifier: Operating System :: OS Independent
Requires-Python: >=3.8
License-File: LICENSE
Requires-Dist: cloudpickle (==2.0.0)
Requires-Dist: grpcio (==1.47.0)
Requires-Dist: protobuf (==3.20.0)
Requires-Dist: pycryptodomex (==3.15.0)
Requires-Dist: requests (==2.28.1)
Requires-Dist: torch (==1.11.0)
Requires-Dist: torchvision (==0.12.0)
Requires-Dist: torchaudio (==0.11.0)
Requires-Dist: tensorboard (==2.8.0)
Requires-Dist: cryptography (>=35.0)
Requires-Dist: gmpy2 (>=2.1.2)
Requires-Dist: tenseal (>=0.3)
